sabarishpyca.py
sabarishpyca-0.0.1.dist-info/LICENSE.txt
sabarishpyca-0.0.1.dist-info/METADATA
sabarishpyca-0.0.1.dist-info/WHEEL
sabarishpyca-0.0.1.dist-info/top_level.txt
sabarishpyca-0.0.1.dist-info/RECORD
